trodesnetwork/__init__.py
trodesnetwork/socket.py
trodesnetwork/trodes/__init__.py
trodesnetwork/trodes/acquisition.py
trodesnetwork/trodes/analog.py
trodesnetwork/trodes/console_command.py
trodesnetwork/trodes/data.py
trodesnetwork/trodes/digital.py
trodesnetwork/trodes/events.py
trodesnetwork/trodes/file.py
trodesnetwork/trodes/hardware_channel_map.py
trodesnetwork/trodes/info_client.py
trodesnetwork/trodes/statescript.py
trodesnetwork/trodes/trodes.py
trodesnetwork/trodes/trodes_client.py
trodesnetwork-0.1.0.dist-info/LICENSE
trodesnetwork-0.1.0.dist-info/METADATA
trodesnetwork-0.1.0.dist-info/WHEEL
trodesnetwork-0.1.0.dist-info/top_level.txt
trodesnetwork-0.1.0.dist-info/RECORD
